{"cameraMode":{"drawMode":0,"name":"Shaded","section":"Shading Mode"},"sceneLighting":true,"audioPlay":false,"sceneViewState":{"m_AlwaysRefresh":false,"showFog":true,"showSkybox":false,"showFlares":true,"showImageEffects":true,"showParticleSystems":true,"showVisualEffectGraphs":true,"m_FxEnabled":true},"in2DMode":false,"pivot":{"x":-26.468643188476564,"y":8.12837028503418,"z":0.5579425692558289},"rotation":{"x":-0.2592834234237671,"y":0.6961409449577332,"z":-0.30215954780578616,"w":-0.5973966717720032},"size":0.3535533845424652,"orthographic":false}